[
    {
        "id": 1,
        "img": "/svg/doors/door.svg",
        "availability": "В наличии",
        "type": "для квартиры",
        "title": "Противопожарная одностворчатая дверь",
        "price": "65 065",
        "number": "60 РАЛ 3002"
    },
    {
        "id": 2,
        "img": "/svg/doors/door.svg",
        "availability": "В наличии",
        "type": "для квартиры",
        "title": "Противопожарная одностворчатая дверь",
        "price": "60 000",
        "number": "60 РАЛ 3002"
    },
    {
        "id": 3,
        "img": "/svg/doors/door.svg",
        "availability": "В наличии",
        "type": "для квартиры",
        "title": "Противопожарная одностворчатая дверь",
        "price": "45 055",
        "number": "60 РАЛ 3002"
    },
    {
        "id": 4,
        "img": "/svg/doors/door.svg",
        "availability": "В наличии",
        "type": "для квартиры",
        "title": "Противопожарная одностворчатая дверь",
        "price": "73 077",
        "number": "60 РАЛ 3002"
    }
]
